clidemo/__init__.py
clidemo/main.py
clidemo-0.1.0.dist-info/entry_points.txt
clidemo-0.1.0.dist-info/WHEEL
clidemo-0.1.0.dist-info/METADATA
clidemo-0.1.0.dist-info/RECORD
